rpy_bridge/__init__.py
rpy_bridge/compare.py
rpy_bridge/convert.py
rpy_bridge/core.py
rpy_bridge/dataframe.py
rpy_bridge/env.py
rpy_bridge/logging.py
rpy_bridge/py.typed
rpy_bridge/renv.py
rpy_bridge/rpy2_loader.py
rpy_bridge-0.5.1.dist-info/licenses/LICENSE
rpy_bridge-0.5.1.dist-info/METADATA
rpy_bridge-0.5.1.dist-info/WHEEL
rpy_bridge-0.5.1.dist-info/top_level.txt
rpy_bridge-0.5.1.dist-info/RECORD
