Metadata-Version: 2.4
Name: rpy-bridge
Version: 0.5.1
Summary: Python-to-R interoperability engine with environment management, type-safe conversions, data normalization, and safe R function execution.
Author-email: Victoria Cheung <victoriakcheung@gmail.com>
License: MIT License
Project-URL: Homepage, https://github.com/vic-cheung/rpy-bridge
Project-URL: Issue Tracker, https://github.com/vic-cheung/rpy-bridge/issues
Keywords: python,r,rpy2,python-r,interoperability,data-science,statistics,bioinformatics
Classifier: License :: OSI Approved :: MIT License
Classifier: Programming Language :: Python
Classifier: Programming Language :: Python :: 3
Classifier: Programming Language :: Python :: 3.11
Classifier: Programming Language :: Python :: 3.12
Classifier: Intended Audience :: Developers
Classifier: Intended Audience :: Science/Research
Classifier: Topic :: Scientific/Engineering :: Bio-Informatics
Classifier: Topic :: Scientific/Engineering :: Information Analysis
Classifier: Topic :: Software Development :: Libraries :: Python Modules
Requires-Python: >=3.11
License-File: LICENSE
Requires-Dist: numpy>=1.24
Requires-Dist: pandas>=2.0
Requires-Dist: loguru>=0.7
Provides-Extra: r
Requires-Dist: rpy2>=3.5; extra == "r"
Provides-Extra: dev
Requires-Dist: ipykernel>=7.1.0; extra == "dev"
Requires-Dist: pytest>=8.0; extra == "dev"
Requires-Dist: ruff>=0.6; extra == "dev"
Requires-Dist: build>=1.0; extra == "dev"
Requires-Dist: twine>=4.0; extra == "dev"
Requires-Dist: certifi>=2025.0; extra == "dev"
Requires-Dist: ty>=0.0.1a34; extra == "dev"
Provides-Extra: docs
Requires-Dist: sphinx; extra == "docs"
Requires-Dist: myst-parser; extra == "docs"
Dynamic: license-file
